docx_coreprop_writer/__init__.py
docx_coreprop_writer/version.py
docx_coreprop_writer-0.0.10.dist-info/LICENSE
docx_coreprop_writer-0.0.10.dist-info/METADATA
docx_coreprop_writer-0.0.10.dist-info/WHEEL
docx_coreprop_writer-0.0.10.dist-info/entry_points.txt
docx_coreprop_writer-0.0.10.dist-info/top_level.txt
docx_coreprop_writer-0.0.10.dist-info/RECORD
